ressources/picorv32/vec_alu.v
module vec_alu #(
	parameter [9:0] VLEN = 10'd 128,
    parameter [2:0] LANE_WIDTH = 3'b011, // 2^LANE_WIDTH bits per lane (8,16,32,64)
    // LANE_WIDTH * 2^nb_lanes must be less than or equal to VLEN
    parameter [2:0] LANE_I = 3'b000
) (
    input               clk, resetn,
    input      [1:0]    nb_lanes, // 2^nb_lanes lanes used for arith / logic operations
    input      [5:0]    opcode,
    input               run,
    input      [VLEN-1:0] vs1_in,
    input      [VLEN-1:0] vs2_in,
    input      [2:0]    vsew,
    input      [2:0]    op_type, // 001 : vv | 010 : VX | 100 : VI

    output [63:0] vd,
    output [9:0] reg_index,
    output reg       done
);
    localparam [7:0] SHIFTED_LANE_WIDTH = 1 << LANE_WIDTH;
    localparam [8:0] ADD_SHIFTED_LANE_WIDTH = SHIFTED_LANE_WIDTH + 1;
	localparam [2:0] VV = 3'b001;
	localparam [2:0] VX = 3'b010;
	localparam [2:0] VI = 3'b100;

    reg [9:0]  byte_i;
    reg [64:0] temp_vreg; // 64 + 1 for carry out
    reg [3:0]  in_reg_offset;

    reg cout;

    integer index;

    reg [63:0] vs1;
    reg [63:0] vs2;

    assign reg_index = index;

    assign vd = temp_vreg[0 +: 64];

    always @(posedge clk) begin
        if (!resetn) begin
            byte_i <= 0;
            temp_vreg <= 0;
            in_reg_offset <= 0;
            cout <= 0;
            vs1 <= 0;
            vs2 <= 0;
            done <= 0;
            index = 0;
        end else if (run) begin
            if (!done) begin
                index = ((LANE_I + byte_i) << (vsew + 3)) + (in_reg_offset << LANE_WIDTH);
                
                case (vsew)
                    // 8 bits
                    3'b000: begin
                        vs1 = {{56{1'b0}}, vs1_in[op_type == VV ? index : (in_reg_offset << LANE_WIDTH) +: 8]};
                        vs2 = {{56{1'b0}}, vs2_in[index +: 8]};
                    end
                    // 16 bits
                    3'b001: begin
                        vs1 = {{48{1'b0}}, vs1_in[op_type == VV ? index : (in_reg_offset << LANE_WIDTH) +: 16]};
                        vs2 = {{48{1'b0}}, vs2_in[index +: 16]};
                    end
                    // 32 bits
                    3'b010: begin
                        vs1 = {{32{1'b0}}, vs1_in[op_type == VV ? index : (in_reg_offset << LANE_WIDTH) +: 32]};
                        vs2 = {{32{1'b0}}, vs2_in[index +: 32]};
                    end
                    // 64 bits
                    3'b011: begin
                        vs1 = vs1_in[op_type == VV ? index : (in_reg_offset << LANE_WIDTH) +: 64];
                        vs2 = vs2_in[index +: 64];
                    end
                endcase

                case (opcode)
                    // vand
                    6'b001001: temp_vreg[0 +: SHIFTED_LANE_WIDTH] = vs1[0 +: SHIFTED_LANE_WIDTH] & vs2[0 +: SHIFTED_LANE_WIDTH];
                    // vor
                    6'b001010: temp_vreg[0 +: SHIFTED_LANE_WIDTH] = vs1[0 +: SHIFTED_LANE_WIDTH] | vs2[0 +: SHIFTED_LANE_WIDTH];
                    // vxor
                    6'b001011: temp_vreg[0 +: SHIFTED_LANE_WIDTH] = vs1[0 +: SHIFTED_LANE_WIDTH] ^ vs2[0 +: SHIFTED_LANE_WIDTH];
                    // vadd
                    6'b000000: begin
                        temp_vreg[0 +: ADD_SHIFTED_LANE_WIDTH] = vs1[0 +: SHIFTED_LANE_WIDTH] + vs2[0 +: SHIFTED_LANE_WIDTH] + cout;
                        cout = temp_vreg[ADD_SHIFTED_LANE_WIDTH - 1];
                        temp_vreg[ADD_SHIFTED_LANE_WIDTH - 1] = 1'b0;
                    end
                endcase

                // $display("lane%d byte_i : %d, reg_off : %d, index : %d", LANE_I, byte_i, in_reg_offset, index);
                done <= byte_i + (1 << nb_lanes) == (VLEN >> (vsew+3)) && in_reg_offset == (vsew + 3 <= LANE_WIDTH ? 0 : (1 << (vsew+3-LANE_WIDTH)) - 1);

                if (vsew + 3 < LANE_WIDTH || in_reg_offset == (vsew + 3 <= LANE_WIDTH ? 0 : (1 << (vsew+3-LANE_WIDTH)) - 1)) begin
                    in_reg_offset = 0;
                    byte_i = byte_i + (1<<nb_lanes);
                end else
                    in_reg_offset = in_reg_offset + 1;

                if (in_reg_offset == 0)
                    cout <= 0;
            end
        end else begin
            byte_i <= 0;
            in_reg_offset <= 0;
            done <= 0;
            index = 0;
        end
    end
endmodule

ressources/picorv32/testbench_vec_alu.v
`timescale 1 ns / 1 ps

`ifndef VERILATOR

`define assert(signal, value) \
        if (signal !== value) begin \
            $display("\n[ERROR] ASSERTION FAILED in %m: signal != value\n"); \
            $finish; \
        end

`define min(a,b) (a < b ? a : b)


module testbench ();
	localparam [2:0] LANE_WIDTH = 3'b101;
	localparam [7:0] SHIFTED_LANE_WIDTH = 1 << LANE_WIDTH;
	localparam [1:0] NB_LANES = 2'b01;
	localparam [9:0] VLEN = 10'd128;
	localparam [4:0] IMM = 5'b00001;
	localparam [31:0] RS1 = 32'h00000001;
	
	localparam [2:0] OP_TYPE = 3'b001;
	localparam [2:0] VV = 3'b001;
	localparam [2:0] VX = 3'b010;
	localparam [2:0] VI = 3'b100;

	localparam [5:0] VAND = 6'b001001;
	localparam [5:0] VOR = 6'b001010;
	localparam [5:0] VXOR = 6'b001011;
	localparam [5:0] VADD = 6'b000000;

	reg clk = 0;
	reg resetn = 0;
	wire trap;

	wire trace_valid;
	wire [35:0] trace_data;
	integer trace_file;

	reg [5:0] opcode;
	reg	run0,run1,run2,run3;
	reg [127:0] vs1;
	reg [127:0] vs2;
	reg [2:0] vsew;

	reg [127:0] vd;
	wire [63:0] vd0, vd1, vd2, vd3;
	wire done0, done1, done2, done3;
	wire [9:0] regi0,regi1,regi2,regi3;

	reg [1:0] nb_lanes;


	task repeat_loop;
		input integer n;
		input print;
		begin
			vd <= 0;
			run0 <= 1;
			if (VLEN >> (vsew+3) > 1 && NB_LANES >= 1) run1 <= 1; else run1 <= 0;
			if (VLEN >> (vsew+3) > 2 && NB_LANES >= 2) run2 <= 1; else run2 <= 0;
			if (VLEN >> (vsew+3) > 3 && NB_LANES >= 2) run3 <= 1; else run3 <= 0;
			repeat (n-1) begin
				run0 <= 1;
				if (VLEN >> (vsew+3) > 1 && NB_LANES >= 1) run1 <= 1; else run1 <= 0;
				if (VLEN >> (vsew+3) > 2 && NB_LANES >= 2) run2 <= 1; else run2 <= 0;
				if (VLEN >> (vsew+3) > 3 && NB_LANES >= 2) run3 <= 1; else run3 <= 0;

				clk <= 1;
				#5;
				clk <= 0;
				#5;
				
				`assert(done0, 1'b0)
				`assert(done1, 1'b0)
				`assert(done2, 1'b0)
				`assert(done3, 1'b0)

				if (vsew + 3 > SHIFTED_LANE_WIDTH) begin // impossible for 8b
					case (vsew)
						3'b001: begin
							vd[regi0 +: 16] = vd0[0 +: 16];
							if (nb_lanes >= 1) vd[regi1 +: 16] = vd1[0 +: 16];
							if (nb_lanes >= 2) vd[regi2 +: 16] = vd2[0 +: 16];
							if (nb_lanes >= 2) vd[regi3 +: 16] = vd3[0 +: 16];
						end
						3'b010: begin
							vd[regi0 +: 32] = vd0[0 +: 32];
							if (nb_lanes >= 1) vd[regi1 +: 32] = vd1[0 +: 32];
							if (nb_lanes >= 2) vd[regi2 +: 32] = vd2[0 +: 32];
							if (nb_lanes >= 2) vd[regi3 +: 32] = vd3[0 +: 32];
						end
						3'b011: begin
							vd[regi0 +: 64] = vd0[0 +: 64];
							if (nb_lanes >= 1) vd[regi1 +: 64] = vd1[0 +: 64];
							if (nb_lanes >= 2) vd[regi2 +: 64] = vd2[0 +: 64];
							if (nb_lanes >= 2) vd[regi3 +: 64] = vd3[0 +: 64];
						end
					endcase
				end else begin
					vd[regi0 +: SHIFTED_LANE_WIDTH] = vd0[0 +: SHIFTED_LANE_WIDTH];
					if (nb_lanes >= 1) vd[regi1 +: SHIFTED_LANE_WIDTH] = vd1[0 +: SHIFTED_LANE_WIDTH];
					if (nb_lanes >= 2) vd[regi2 +: SHIFTED_LANE_WIDTH] = vd2[0 +: SHIFTED_LANE_WIDTH];
					if (nb_lanes >= 2) vd[regi3 +: SHIFTED_LANE_WIDTH] = vd3[0 +: SHIFTED_LANE_WIDTH];
				end
				
				if (print) $display("index1 : %d", regi0);
				if (print) $display("index2 : %d", regi1);
				if (print) $display("index3 : %d", regi2);
				if (print) $display("index4 : %d", regi3);
				if (print) $display("vd : %h", vd);
			end
			clk <= 1;
			#5;
			clk <= 0;
			#5;
			if (vsew + 3 > SHIFTED_LANE_WIDTH) begin // impossible for 8b
				case (vsew)
					3'b001: begin
						vd[regi0 +: 16] = vd0[0 +: 16];
						if (nb_lanes >= 1) vd[regi1 +: 16] = vd1[0 +: 16];
						if (nb_lanes >= 2) vd[regi2 +: 16] = vd2[0 +: 16];
						if (nb_lanes >= 2) vd[regi3 +: 16] = vd3[0 +: 16];
					end
					3'b010: begin
						vd[regi0 +: 32] = vd0[0 +: 32];
						if (nb_lanes >= 1) vd[regi1 +: 32] = vd1[0 +: 32];
						if (nb_lanes >= 2) vd[regi2 +: 32] = vd2[0 +: 32];
						if (nb_lanes >= 2) vd[regi3 +: 32] = vd3[0 +: 32];
					end
					3'b011: begin
						vd[regi0 +: 64] = vd0[0 +: 64];
						if (nb_lanes >= 1) vd[regi1 +: 64] = vd1[0 +: 64];
						if (nb_lanes >= 2) vd[regi2 +: 64] = vd2[0 +: 64];
						if (nb_lanes >= 2) vd[regi3 +: 64] = vd3[0 +: 64];
					end
				endcase
			end else begin
				vd[regi0 +: SHIFTED_LANE_WIDTH] = vd0[0 +: SHIFTED_LANE_WIDTH];
				if (nb_lanes >= 1) vd[regi1 +: SHIFTED_LANE_WIDTH] = vd1[0 +: SHIFTED_LANE_WIDTH];
				if (nb_lanes >= 2) vd[regi2 +: SHIFTED_LANE_WIDTH] = vd2[0 +: SHIFTED_LANE_WIDTH];
				if (nb_lanes >= 2) vd[regi3 +: SHIFTED_LANE_WIDTH] = vd3[0 +: SHIFTED_LANE_WIDTH];
			end
			if (print) $display("index1 : %d", regi0);
			if (print) $display("index2 : %d", regi1);
			if (print) $display("index3 : %d", regi2);
			if (print) $display("index4 : %d", regi3);
			if (print) $display("vd : %h", vd);
		end
	endtask

	initial begin
		$display("+---------------------------------+\n| Test with %2d LANE(S) of %2d bits |\n+---------------------------------+", 1 << NB_LANES, 1 << LANE_WIDTH);

		repeat (200) begin
			clk <= ~clk;
			#5;
		end
		resetn <= 1;
		opcode <= VADD;
		case (OP_TYPE)
			VV: vs1 <= 128'habcdabcdbeefbeef1234567887654321;
			VX: vs1 <= {{96{RS1[31]}}, RS1};
			VI: vs1 <= {{123{IMM[4]}}, IMM};
		endcase
		vs2 <= 128'h8765432112345678beefbeefabcdabcd;
		
		// -------------------------- 8 BITS --------------------------
		vsew <= 3'b000;
		run0 <= 0; run1 <= 0; run2 <= 0; run3 <= 0;
		clk <= 1;
		#5;
		case (`min(VLEN>>(vsew+3), 1 << NB_LANES))
			0,
			1: nb_lanes <= 0;
			2,
			3: nb_lanes <= 1;
			4,
			5,
			6,
			7: nb_lanes <= 2;
			8: nb_lanes <= 3;
		endcase
		clk <= 0;
		#5;
		
		repeat_loop((VLEN >> `min(3, LANE_WIDTH))>>nb_lanes, 1);
		`assert(done0, 1'b1)
		if (nb_lanes >= 1) `assert(done1, 1'b1)
		if (nb_lanes >= 2) `assert(done2, 1'b1)
		if (nb_lanes >= 2) `assert(done3, 1'b1)
		// `assert(vd, 128'h83450301122416681224166883450301)
		// add.vv
		// 3232eeeed0231467d02314673232eeee
		$display("[OK] 8b");

		// -------------------------- 16 BITS --------------------------
		vsew <= 3'b001;
		run0 <= 0; run1 <= 0; run2 <= 0; run3 <= 0;
		clk <= 1;
		#5;
		case (`min(VLEN>>(vsew+3), 1 << NB_LANES))
			0,
			1: nb_lanes <= 0;
			2,
			3: nb_lanes <= 1;
			4,
			5,
			6,
			7: nb_lanes <= 2;
			8: nb_lanes <= 3;
		endcase
		clk <= 0;
		#5;
		
		repeat_loop((VLEN >> `min(4, LANE_WIDTH))>>nb_lanes, 1);
		`assert(done0, 1'b1)
		if (nb_lanes >= 1) `assert(done1, 1'b1)
		if (nb_lanes >= 2) `assert(done2, 1'b1)
		if (nb_lanes >= 2) `assert(done3, 1'b1)
		// `assert(vd, 128'h83450301122416681224166883450301)
		// add.vv
		// 3332eeeed1231567d12315673332eeee
		$display("[OK] 16b");

		// -------------------------- 32 BITS --------------------------
		vsew <= 3'b010;
		run0 <= 0; run1 <= 0; run2 <= 0; run3 <= 0;
		clk <= 1;
		#5;
		case (`min(VLEN>>(vsew+3), 1 << NB_LANES))
			0,
			1: nb_lanes <= 0;
			2,
			3: nb_lanes <= 1;
			4,
			5,
			6,
			7: nb_lanes <= 2;
			8: nb_lanes <= 3;
		endcase
		clk <= 0;
		#5;
		
		repeat_loop((VLEN >> `min(5, LANE_WIDTH))>>nb_lanes, 1);
		`assert(done0, 1'b1)
		if (nb_lanes >= 1) `assert(done1, 1'b1)
		if (nb_lanes >= 2) `assert(done2, 1'b1)
		if (nb_lanes >= 2) `assert(done3, 1'b1)
		// `assert(vd, 128'h83450301122416681224166883450301)
		// add.vv
		// 3332eeeed1241567d12415673332eeee
		$display("[OK] 32b");
		
		// -------------------------- 64 BITS --------------------------
		vsew <= 3'b011;
		run0 <= 0; run1 <= 0; run2 <= 0; run3 <= 0;
		clk <= 1;
		#5;
		case (`min(VLEN>>(vsew+3), 1 << NB_LANES))
			0,
			1: nb_lanes <= 0;
			2,
			3: nb_lanes <= 1;
			4,
			5,
			6,
			7: nb_lanes <= 2;
			8: nb_lanes <= 3;
		endcase
		clk <= 0;
		#5;

		repeat_loop((VLEN >> `min(6, LANE_WIDTH))>>nb_lanes, 1);
		`assert(done0, 1'b1)
		if (nb_lanes >= 1) `assert(done1, 1'b1)
		if (nb_lanes >= 2) `assert(done2, 1'b1)
		if (nb_lanes >= 2) `assert(done3, 1'b1)
		// `assert(vd, 128'h83450301122416681224166883450301)
		// add.vv
		// 3332eeeed1241567d12415683332eeee
		$display("[OK] 64b");



		
	end

	initial begin
		if ($test$plusargs("vcd")) begin
			$dumpfile("testbench_vec_alu.vcd");
			$dumpvars(0, testbench);
		end
		repeat (1000000) @(posedge clk);
		$display("TIMEOUT");
		$finish;
	end

	vec_alu #(
		.VLEN (VLEN),
		.LANE_WIDTH (LANE_WIDTH),
		.LANE_I (3'b000)
	) valu0 (
		.clk(clk),
		.resetn(resetn),
		.nb_lanes(nb_lanes),
		.opcode(opcode),
		.run(run0),
		.vs1_in(vs1),
		.vs2_in(vs2),
		.vsew(vsew),
		.op_type(OP_TYPE),
		.vd(vd0),
		.reg_index(regi0),
		.done(done0)
	);
	
	vec_alu #(
		.VLEN (VLEN),
		.LANE_WIDTH (LANE_WIDTH),
		.LANE_I (3'b001)
	) valu1 (
		.clk(clk),
		.resetn(resetn),
		.nb_lanes(nb_lanes),
		.opcode(opcode),
		.run(run1),
		.vs1_in(vs1),
		.vs2_in(vs2),
		.vsew(vsew),
		.op_type(OP_TYPE),
		.vd(vd1),
		.reg_index(regi1),
		.done(done1)
	);
	
	vec_alu #(
		.VLEN (VLEN),
		.LANE_WIDTH (LANE_WIDTH),
		.LANE_I (3'b010)
	) valu2 (
		.clk(clk),
		.resetn(resetn),
		.nb_lanes(nb_lanes),
		.opcode(opcode),
		.run(run2),
		.vs1_in(vs1),
		.vs2_in(vs2),
		.vsew(vsew),
		.op_type(OP_TYPE),
		.vd(vd2),
		.reg_index(regi2),
		.done(done2)
	);
	
	vec_alu #(
		.VLEN (VLEN),
		.LANE_WIDTH (LANE_WIDTH),
		.LANE_I (3'b011)
	) valu3 (
		.clk(clk),
		.resetn(resetn),
		.nb_lanes(nb_lanes),
		.opcode(opcode),
		.run(run3),
		.vs1_in(vs1),
		.vs2_in(vs2),
		.vsew(vsew),
		.op_type(OP_TYPE),
		.vd(vd3),
		.reg_index(regi3),
		.done(done3)
	);
endmodule
`endif

ressources/picorv32/testbench_vec_alu.vcd
$date
	Tue Jun 24 15:50:13 2025
$end
$version
	Icarus Verilog
$end
$timescale
	1ps
$end
$scope module testbench $end
$var wire 64 ! vd3 [63:0] $end
$var wire 64 " vd2 [63:0] $end
$var wire 64 # vd1 [63:0] $end
$var wire 64 $ vd0 [63:0] $end
$var wire 10 % regi3 [9:0] $end
$var wire 10 & regi2 [9:0] $end
$var wire 10 ' regi1 [9:0] $end
$var wire 10 ( regi0 [9:0] $end
$var wire 1 ) done3 $end
$var wire 1 * done2 $end
$var wire 1 + done1 $end
$var wire 1 , done0 $end
$var reg 1 - clk $end
$var reg 2 . nb_lanes [1:0] $end
$var reg 6 / opcode [5:0] $end
$var reg 1 0 resetn $end
$var reg 1 1 run0 $end
$var reg 1 2 run1 $end
$var reg 1 3 run2 $end
$var reg 1 4 run3 $end
$var reg 128 5 vd [127:0] $end
$var reg 128 6 vs1 [127:0] $end
$var reg 128 7 vs2 [127:0] $end
$var reg 3 8 vsew [2:0] $end
$scope module valu0 $end
$var wire 1 - clk $end
$var wire 2 9 nb_lanes [1:0] $end
$var wire 3 : op_type [2:0] $end
$var wire 6 ; opcode [5:0] $end
$var wire 1 0 resetn $end
$var wire 1 1 run $end
$var wire 128 < vs1_in [127:0] $end
$var wire 128 = vs2_in [127:0] $end
$var wire 3 > vsew [2:0] $end
$var wire 64 ? vd [63:0] $end
$var wire 10 @ reg_index [9:0] $end
$var reg 10 A byte_i [9:0] $end
$var reg 1 B cout $end
$var reg 1 , done $end
$var reg 4 C in_reg_offset [3:0] $end
$var reg 65 D temp_vreg [64:0] $end
$var reg 64 E vs1 [63:0] $end
$var reg 64 F vs2 [63:0] $end
$var integer 32 G index [31:0] $end
$upscope $end
$scope module valu1 $end
$var wire 1 - clk $end
$var wire 2 H nb_lanes [1:0] $end
$var wire 3 I op_type [2:0] $end
$var wire 6 J opcode [5:0] $end
$var wire 1 0 resetn $end
$var wire 1 2 run $end
$var wire 128 K vs1_in [127:0] $end
$var wire 128 L vs2_in [127:0] $end
$var wire 3 M vsew [2:0] $end
$var wire 64 N vd [63:0] $end
$var wire 10 O reg_index [9:0] $end
$var reg 10 P byte_i [9:0] $end
$var reg 1 Q cout $end
$var reg 1 + done $end
$var reg 4 R in_reg_offset [3:0] $end
$var reg 65 S temp_vreg [64:0] $end
$var reg 64 T vs1 [63:0] $end
$var reg 64 U vs2 [63:0] $end
$var integer 32 V index [31:0] $end
$upscope $end
$scope module valu2 $end
$var wire 1 - clk $end
$var wire 2 W nb_lanes [1:0] $end
$var wire 3 X op_type [2:0] $end
$var wire 6 Y opcode [5:0] $end
$var wire 1 0 resetn $end
$var wire 1 3 run $end
$var wire 128 Z vs1_in [127:0] $end
$var wire 128 [ vs2_in [127:0] $end
$var wire 3 \ vsew [2:0] $end
$var wire 64 ] vd [63:0] $end
$var wire 10 ^ reg_index [9:0] $end
$var reg 10 _ byte_i [9:0] $end
$var reg 1 ` cout $end
$var reg 1 * done $end
$var reg 4 a in_reg_offset [3:0] $end
$var reg 65 b temp_vreg [64:0] $end
$var reg 64 c vs1 [63:0] $end
$var reg 64 d vs2 [63:0] $end
$var integer 32 e index [31:0] $end
$upscope $end
$scope module valu3 $end
$var wire 1 - clk $end
$var wire 2 f nb_lanes [1:0] $end
$var wire 3 g op_type [2:0] $end
$var wire 6 h opcode [5:0] $end
$var wire 1 0 resetn $end
$var wire 1 4 run $end
$var wire 128 i vs1_in [127:0] $end
$var wire 128 j vs2_in [127:0] $end
$var wire 3 k vsew [2:0] $end
$var wire 64 l vd [63:0] $end
$var wire 10 m reg_index [9:0] $end
$var reg 10 n byte_i [9:0] $end
$var reg 1 o cout $end
$var reg 1 ) done $end
$var reg 4 p in_reg_offset [3:0] $end
$var reg 65 q temp_vreg [64:0] $end
$var reg 64 r vs1 [63:0] $end
$var reg 64 s vs2 [63:0] $end
$var integer 32 t index [31:0] $end
$upscope $end
$scope task repeat_loop $end
$var reg 1 u print $end
$var integer 32 v n [31:0] $end
$upscope $end
$upscope $end
$enddefinitions $end
#0
$dumpvars
bx v
xu
b0 t
b0 s
b0 r
b0 q
b0 p
0o
b0 n
b0 m
b0 l
bx k
bx j
bx i
bx h
b1 g
bx f
b0 e
b0 d
b0 c
b0 b
b0 a
0`
b0 _
b0 ^
b0 ]
bx \
bx [
bx Z
bx Y
b1 X
bx W
b0 V
b0 U
b0 T
b0 S
b0 R
0Q
b0 P
b0 O
b0 N
bx M
bx L
bx K
bx J
b1 I
bx H
b0 G
b0 F
b0 E
b0 D
b0 C
0B
b0 A
b0 @
b0 ?
bx >
bx =
bx <
bx ;
b1 :
bx 9
bx 8
bx 7
bx 6
bx 5
x4
x3
x2
x1
00
bx /
bx .
1-
0,
0+
0*
0)
b0 (
b0 '
b0 &
b0 %
b0 $
b0 #
b0 "
b0 !
$end
#5000
0-
#10000
1-
#15000
0-
#20000
1-
#25000
0-
#30000
1-
#35000
0-
#40000
1-
#45000
0-
#50000
1-
#55000
0-
#60000
1-
#65000
0-
#70000
1-
#75000
0-
#80000
1-
#85000
0-
#90000
1-
#95000
0-
#100000
1-
#105000
0-
#110000
1-
#115000
0-
#120000
1-
#125000
0-
#130000
1-
#135000
0-
#140000
1-
#145000
0-
#150000
1-
#155000
0-
#160000
1-
#165000
0-
#170000
1-
#175000
0-
#180000
1-
#185000
0-
#190000
1-
#195000
0-
#200000
1-
#205000
0-
#210000
1-
#215000
0-
#220000
1-
#225000
0-
#230000
1-
#235000
0-
#240000
1-
#245000
0-
#250000
1-
#255000
0-
#260000
1-
#265000
0-
#270000
1-
#275000
0-
#280000
1-
#285000
0-
#290000
1-
#295000
0-
#300000
1-
#305000
0-
#310000
1-
#315000
0-
#320000
1-
#325000
0-
#330000
1-
#335000
0-
#340000
1-
#345000
0-
#350000
1-
#355000
0-
#360000
1-
#365000
0-
#370000
1-
#375000
0-
#380000
1-
#385000
0-
#390000
1-
#395000
0-
#400000
1-
#405000
0-
#410000
1-
#415000
0-
#420000
1-
#425000
0-
#430000
1-
#435000
0-
#440000
1-
#445000
0-
#450000
1-
#455000
0-
#460000
1-
#465000
0-
#470000
1-
#475000
0-
#480000
1-
#485000
0-
#490000
1-
#495000
0-
#500000
1-
#505000
0-
#510000
1-
#515000
0-
#520000
1-
#525000
0-
#530000
1-
#535000
0-
#540000
1-
#545000
0-
#550000
1-
#555000
0-
#560000
1-
#565000
0-
#570000
1-
#575000
0-
#580000
1-
#585000
0-
#590000
1-
#595000
0-
#600000
1-
#605000
0-
#610000
1-
#615000
0-
#620000
1-
#625000
0-
#630000
1-
#635000
0-
#640000
1-
#645000
0-
#650000
1-
#655000
0-
#660000
1-
#665000
0-
#670000
1-
#675000
0-
#680000
1-
#685000
0-
#690000
1-
#695000
0-
#700000
1-
#705000
0-
#710000
1-
#715000
0-
#720000
1-
#725000
0-
#730000
1-
#735000
0-
#740000
1-
#745000
0-
#750000
1-
#755000
0-
#760000
1-
#765000
0-
#770000
1-
#775000
0-
#780000
1-
#785000
0-
#790000
1-
#795000
0-
#800000
1-
#805000
0-
#810000
1-
#815000
0-
#820000
1-
#825000
0-
#830000
1-
#835000
0-
#840000
1-
#845000
0-
#850000
1-
#855000
0-
#860000
1-
#865000
0-
#870000
1-
#875000
0-
#880000
1-
#885000
0-
#890000
1-
#895000
0-
#900000
1-
#905000
0-
#910000
1-
#915000
0-
#920000
1-
#925000
0-
#930000
1-
#935000
0-
#940000
1-
#945000
0-
#950000
1-
#955000
0-
#960000
1-
#965000
0-
#970000
1-
#975000
0-
#980000
1-
#985000
0-
#990000
1-
#995000
0-
#1000000
1-
04
03
02
01
b0 8
b0 >
b0 M
b0 \
b0 k
b10000111011001010100001100100001000100100011010001010110011110001011111011101111101111101110111110101011110011011010101111001101 7
b10000111011001010100001100100001000100100011010001010110011110001011111011101111101111101110111110101011110011011010101111001101 =
b10000111011001010100001100100001000100100011010001010110011110001011111011101111101111101110111110101011110011011010101111001101 L
b10000111011001010100001100100001000100100011010001010110011110001011111011101111101111101110111110101011110011011010101111001101 [
b10000111011001010100001100100001000100100011010001010110011110001011111011101111101111101110111110101011110011011010101111001101 j
b10101011110011011010101111001101101111101110111110111110111011110001001000110100010101100111100010000111011001010100001100100001 6
b10101011110011011010101111001101101111101110111110111110111011110001001000110100010101100111100010000111011001010100001100100001 <
b10101011110011011010101111001101101111101110111110111110111011110001001000110100010101100111100010000111011001010100001100100001 K
b10101011110011011010101111001101101111101110111110111110111011110001001000110100010101100111100010000111011001010100001100100001 Z
b10101011110011011010101111001101101111101110111110111110111011110001001000110100010101100111100010000111011001010100001100100001 i
b0 /
b0 ;
b0 J
b0 Y
b0 h
10
#1005000
0-
b1 .
b1 9
b1 H
b1 W
b1 f
#1010000
b11101110 #
b11101110 N
b1000 '
b1000 O
b11101110 $
b11101110 ?
b10 P
b11101110 S
b10101011 U
b1000011 T
b1000 V
b10 A
b11101110 D
b11001101 F
b100001 E
1-
12
11
b0 5
1u
b1000 v
#1015000
0-
#1020000
b100110010 $
b100110010 ?
b10000 (
b10000 @
b100110010 #
b100110010 N
b11000 '
b11000 O
b100 A
b100110010 D
b1100101 E
b10000 G
b100 P
b100110010 S
b10000111 T
b11000 V
1-
b1110111011101110 5
#1025000
0-
#1030000
b100010100 #
b100010100 N
b101000 '
b101000 O
b101100111 $
b101100111 ?
b100000 (
b100000 @
b110 P
b100010100 S
b10111110 U
b1010110 T
b101000 V
b110 A
b101100111 D
b11101111 F
b1111000 E
b100000 G
1-
b100110010001100101110111011101110 5
#1035000
0-
#1040000
b100100011 $
b100100011 ?
b110000 (
b110000 @
b11010000 #
b11010000 N
b111000 '
b111000 O
b1000 A
b100100011 D
b110100 E
b110000 G
b1000 P
b11010000 S
b10010 T
b111000 V
1-
b1000101000110011100110010001100101110111011101110 5
#1045000
0-
#1050000
b100010100 #
b100010100 N
b1001000 '
b1001000 O
b101100111 $
b101100111 ?
b1000000 (
b1000000 @
b1010 P
b100010100 S
b1010110 U
b10111110 T
b1001000 V
b1010 A
b101100111 D
b1111000 F
b11101111 E
b1000000 G
1-
b1101000000100011000101000110011100110010001100101110111011101110 5
#1055000
0-
#1060000
b100100011 $
b100100011 ?
b1010000 (
b1010000 @
b11010000 #
b11010000 N
b1011000 '
b1011000 O
b1100 A
b100100011 D
b110100 F
b1010000 G
b1100 P
b11010000 S
b10010 U
b1011000 V
1-
b100010100011001111101000000100011000101000110011100110010001100101110111011101110 5
#1065000
0-
#1070000
b11101110 #
b11101110 N
b1101000 '
b1101000 O
b11101110 $
b11101110 ?
b1100000 (
b1100000 @
b1110 P
b11101110 S
b1000011 U
b10101011 T
b1101000 V
b1110 A
b11101110 D
b100001 F
b11001101 E
b1100000 G
1-
b110100000010001100010100011001111101000000100011000101000110011100110010001100101110111011101110 5
#1075000
0-
#1080000
1,
1+
b100110010 $
b100110010 ?
b1110000 (
b1110000 @
b100110010 #
b100110010 N
b1111000 '
b1111000 O
b10000 A
b100110010 D
b1100101 F
b1110000 G
b10000 P
b100110010 S
b10000111 U
b1111000 V
1-
b1110111011101110110100000010001100010100011001111101000000100011000101000110011100110010001100101110111011101110 5
#1085000
0-
#1090000
0+
b0 P
0,
b0 A
b0 '
b0 O
b0 (
b0 @
b0 V
b0 G
1-
02
01
b1 8
b1 >
b1 M
b1 \
b1 k
b110010001100101110111011101110110100000010001100010100011001111101000000100011000101000110011100110010001100101110111011101110 5
#1095000
0-
#1100000
b1110111011101110 $
b1110111011101110 ?
b10011001100110010 #
b10011001100110010 N
b10000 '
b10000 O
b10 A
b1110111011101110 D
b1010101111001101 F
b100001100100001 E
b10 P
b10011001100110010 S
b1010101111001101 U
b1000011101100101 T
b10000 V
1-
12
11
b0 5
b100 v
#1105000
0-
#1110000
b1101000100100011 #
b1101000100100011 N
b110000 '
b110000 O
b10001010101100111 $
b10001010101100111 ?
b100000 (
b100000 @
b100 P
b1101000100100011 S
b1011111011101111 U
b1001000110100 T
b110000 V
b100 A
b10001010101100111 D
b1011111011101111 F
b101011001111000 E
b100000 G
1-
b100110011001100101110111011101110 5
#1115000
0-
#1120000
b1000000 (
b1000000 @
b1010000 '
b1010000 O
b110 A
b101011001111000 F
b1011111011101111 E
b1000000 G
b110 P
b1001000110100 U
b1011111011101111 T
b1010000 V
1-
b1101000100100011000101010110011100110011001100101110111011101110 5
#1125000
0-
#1130000
1+
1,
b10011001100110010 #
b10011001100110010 N
b1110000 '
b1110000 O
b1110111011101110 $
b1110111011101110 ?
b1100000 (
b1100000 @
b1000 P
b10011001100110010 S
b1000011101100101 U
b1010101111001101 T
b1110000 V
b1000 A
b1110111011101110 D
b100001100100001 F
b1010101111001101 E
b1100000 G
1-
b110100010010001100010101011001111101000100100011000101010110011100110011001100101110111011101110 5
#1135000
0-
#1140000
0,
b0 A
0+
b0 P
b0 (
b0 @
b0 '
b0 O
b0 G
b0 V
1-
02
01
b10 8
b10 >
b10 M
b10 \
b10 k
b110011001100101110111011101110110100010010001100010101011001111101000100100011000101010110011100110011001100101110111011101110 5
#1145000
0-
#1150000
b11010001001001000001010101100111 #
b11010001001001000001010101100111 N
b100000 '
b100000 O
b110011001100101110111011101110 $
b110011001100101110111011101110 ?
b10 P
b11010001001001000001010101100111 S
b10111110111011111011111011101111 U
b10010001101000101011001111000 T
b100000 V
b10 A
0B
b110011001100101110111011101110 D
b10101011110011011010101111001101 F
b10000111011001010100001100100001 E
1-
12
11
b0 5
b10 v
#1155000
0-
